minion_data/__init__.py
minion_data/__main__.py
minion_data/dataset_pb2.py
minion_data/dataset_pb2.pyi
minion_data/inspect/__init__.py
minion_data/inspect/_inspect.py
minion_data/preparation/__init__.py
minion_data/preparation/_chiron_out.py
minion_data/preparation/_old_metrichon.py
minion_data/preparation/_preparation.py
minion_data/preparation/_re_squiggled.py
minion_data/preparation/_signal_label.py
minion_data/preparation/align_utils.py
minion_data/preparation/bioinf_utils.py
minion_data/preparation/common.py
minion_data-0.2.1.dist-info/DESCRIPTION.rst
minion_data-0.2.1.dist-info/LICENSE.txt
minion_data-0.2.1.dist-info/METADATA
minion_data-0.2.1.dist-info/RECORD
minion_data-0.2.1.dist-info/WHEEL
minion_data-0.2.1.dist-info/metadata.json
minion_data-0.2.1.dist-info/top_level.txt
