Metadata-Version: 2.0
Name: minion-data
Version: 0.2.1
Summary: UNKNOWN
Home-page: https://github.com/nmiculinic/minion-data
Author: Neven Miculinic
Author-email: neven.miculinic@gmail.com
License: UNKNOWN
Project-URL: Source, https://github.com/nmiculinic/minion-data/
Platform: UNKNOWN
Classifier: Development Status :: 3 - Alpha
Classifier: Intended Audience :: Developers
Classifier: Topic :: Scientific/Engineering :: Bio-Informatics
Classifier: License :: OSI Approved :: MIT License
Classifier: Programming Language :: Python :: 3
Classifier: Programming Language :: Python :: 3.6
Classifier: Programming Language :: Python :: 3 :: Only
Requires-Dist: grpcio-tools (>=1.11)
Requires-Dist: mypy-protobuf (>=1.3)
Requires-Dist: numpy (>=1.14.0)
Requires-Dist: pandas (>=0.22.0)
Requires-Dist: pysam (>=0.14.0)
Requires-Dist: tqdm (>=4.23.0)
